routing_telethon/__init__.py
routing_telethon/bot.py
routing_telethon/bot_logging.py
routing_telethon/data.py
routing_telethon/utils.py
tests/__init__.py
routing_telethon-0.0.2.dist-info/LICENSE
routing_telethon-0.0.2.dist-info/METADATA
routing_telethon-0.0.2.dist-info/WHEEL
routing_telethon-0.0.2.dist-info/top_level.txt
routing_telethon-0.0.2.dist-info/RECORD
