Metadata-Version: 2.1
Name: routing-telethon
Version: 0.0.2
Summary: A package with convenient routing for writing bots in Telethon
Home-page: https://github.com/Arseny-Tokmancev/routing_telethon
Author: Arseny Tokmancev
License: UNKNOWN
Platform: UNKNOWN
Classifier: Programming Language :: Python :: 3
Classifier: License :: OSI Approved :: MIT License
Classifier: Operating System :: OS Independent
Requires-Python: >=3.7
Requires-Dist: telethon (>=1.16.4)
Requires-Dist: sqlalchemy (>=1.3.19)
